AUTHORS.rst
CONTRIBUTING.rst
HISTORY.rst
LICENSE
MANIFEST.in
README.rst
setup.cfg
setup.py
auth0db/__init__.py
auth0db/apps.py
auth0db/backends.py
auth0db/compatibility.py
auth0db/exceptions.py
auth0db/forms.py
auth0db/models.py
auth0db/urls.py
auth0db.egg-info/PKG-INFO
auth0db.egg-info/SOURCES.txt
auth0db.egg-info/dependency_links.txt
auth0db.egg-info/not-zip-safe
auth0db.egg-info/requires.txt
auth0db.egg-info/top_level.txt
tests/__init__.py
tests/test_settings.py
tests/test_integrations/__init__.py
tests/test_integrations/test_backend_integration.py
tests/test_integrations/test_forms_integration.py
tests/test_units/__init__.py
tests/test_units/test_forms.py