Metadata-Version: 1.1
Name: auth0db
Version: 0.1.0
Summary: Auth0 authentication backend for Django
Home-page: https://github.com/bretth/auth0db
Author: Brett Haydon
Author-email: brett@haydon.id.au
License: ISCL
Keywords: auth0db
Platform: UNKNOWN
Classifier: Development Status :: 2 - Pre-Alpha
Classifier: Intended Audience :: Developers
Classifier: License :: OSI Approved :: ISC License (ISCL)
Classifier: Natural Language :: English
Classifier: Programming Language :: Python :: 2
Classifier: Programming Language :: Python :: 2.7
Classifier: Programming Language :: Python :: 3
Classifier: Programming Language :: Python :: 3.4
Classifier: Programming Language :: Python :: 3.5
